MANIFEST.in
README.md
pyproject.toml
pypl2/__init__.py
pypl2/_old_pypl2lib.py
pypl2/pypl2api.py
pypl2/pypl2lib.py
pypl2.egg-info/PKG-INFO
pypl2.egg-info/SOURCES.txt
pypl2.egg-info/dependency_links.txt
pypl2.egg-info/requires.txt
pypl2.egg-info/top_level.txt
pypl2/bin/PL2FileReader.dll
pypl2/bin/PL2FileReader64.dll
pypl2/legacy/__init__.py
pypl2/legacy/pypl2api.py
pypl2/legacy/pypl2lib.py