Metadata-Version: 2.4
Name: pypl2
Version: 0.1.3
Summary: Python wrapper for PL2FileReader dll.
Author-email: Nikhil Chandra <nikhil@plexon.com>, Chris Heydrick <chris@plexon.com>
Requires-Python: >=3.9
Requires-Dist: numpy==1.26.4
Requires-Dist: pypixelmapdump>=0.1.3
